bmigraph/__init__.py
bmigraph/calculate_bmi.py
bmigraph/exercise_plan.py
bmigraph/project_bmi.py
bmigraph/project_calories.py
bmigraph-1.4.0.dist-info/METADATA
bmigraph-1.4.0.dist-info/WHEEL
bmigraph-1.4.0.dist-info/LICENSE
bmigraph-1.4.0.dist-info/RECORD
