Metadata-Version: 2.1
Name: bmigraph
Version: 1.4.0
Summary: A BMI calculator and more!
License: MIT
Author: Qurat-ul-Ain Azim, Natalie Cho, HanChen Wang, Kelvin Wong
Requires-Python: >=3.9
Classifier: License :: OSI Approved :: MIT License
Classifier: Programming Language :: Python :: 3
Classifier: Programming Language :: Python :: 3.9
Classifier: Programming Language :: Python :: 3.10
Classifier: Programming Language :: Python :: 3.11
Requires-Dist: plotly (>=5.12.0)
Requires-Dist: plotly-express (>=0.4.1,<0.5.0)
